Metadata-Version: 2.1
Name: complimenter
Version: 1.0
Summary: Create random compliments
Home-page: UNKNOWN
Author: Mohd Sabahat
Author-email: mohdsabahat123@gmail.com
License: UNKNOWN
Keywords: generator,compliments
Platform: UNKNOWN
Classifier: Programming Language :: Python :: 3
Requires-Python: >=3.6
